[
    {"text": "show me the top rated books", "intent": "top_rated_books"},
    {"text": "what are the highest rated books", "intent": "top_rated_books"},
    {"text": "give me the best books", "intent": "top_rated_books"},
    {"text": "recommend some top books", "intent": "top_rated_books"},
    {"text": "which books have the best ratings", "intent": "top_rated_books"},
    {"text": "I want to see the most popular books", "intent": "top_rated_books"},
    {"text": "top 5 books please", "intent": "top_rated_books"},
    {"text": "what are the best novels", "intent": "top_rated_books"},
    {"text": "list the highest rated novels", "intent": "top_rated_books"},
    {"text": "show the books with top ratings", "intent": "top_rated_books"},

    {"text": "show me the best books by Stephen King", "intent": "get_books_by_author"},
    {"text": "what are the top rated books from J.K. Rowling", "intent": "get_books_by_author"},
    {"text": "recommend the highest rated books by Agatha Christie", "intent": "get_books_by_author"},
    {"text": "give me top books by Dan Brown", "intent": "get_books_by_author"},
    {"text": "list Stephen King's most popular books", "intent": "get_books_by_author"},
    {"text": "show me J.R.R. Tolkien's top rated books", "intent": "get_books_by_author"},
    {"text": "best novels by George Orwell", "intent": "get_books_by_author"},
    {"text": "highest rated books from Suzanne Collins", "intent": "get_books_by_author"},
    {"text": "what are the top books by Neil Gaiman", "intent": "get_books_by_author"},
    {"text": "recommend top rated books by authors like Jane Austen", "intent": "get_books_by_author"},

    {"text": "find the book Dune", "intent": "search_by_title"},
    {"text": "search for The Hobbit", "intent": "search_by_title"},
    {"text": "where can I find 1984", "intent": "search_by_title"},
    {"text": "look up Brave New World", "intent": "search_by_title"},
    {"text": "find Pride and Prejudice", "intent": "search_by_title"},
    {"text": "search for The Great Gatsby", "intent": "search_by_title"},
    {"text": "show me War and Peace", "intent": "search_by_title"},
    {"text": "look up To Kill a Mockingbird", "intent": "search_by_title"},
    {"text": "find Moby Dick", "intent": "search_by_title"},
    {"text": "search for Harry Potter and the Sorcerer's Stone", "intent": "search_by_title"},

    {"text": "tell me about Dune", "intent": "get_details"},
    {"text": "give me details about 1984", "intent": "get_details"},
    {"text": "what information is there for The Hobbit", "intent": "get_details"},
    {"text": "show me details for Brave New World", "intent": "get_details"},
    {"text": "book info for Pride and Prejudice", "intent": "get_details"},
    {"text": "I want to know about The Great Gatsby", "intent": "get_details"},
    {"text": "details for War and Peace", "intent": "get_details"},
    {"text": "information on To Kill a Mockingbird", "intent": "get_details"},
    {"text": "give me the details of Moby Dick", "intent": "get_details"},
    {"text": "what can you tell me about Harry Potter and the Sorcerer's Stone", "intent": "get_details"}
]
